{
  "RootNamespace": "Chirkut",
  "ServerTypings": {
    "LocalTexts": true
  },
  "Restore": {
    "Exclude": [
      "/wwwroot/Scripts/serenity/Serenity.CoreLib*.*"
    ]
  },
  "Connections": [
    {
      "Key": "Main",
      "Tables": [
        {
          "Tablename": "dbo.BoniAdam",
          "Identifier": "BoniAdam",
          "Module": "AdminModule",
          "PermissionKey": "Administration:General"
        },
        {
          "Tablename": "dbo.KarzeHasana",
          "Identifier": "KarzeHasana",
          "Module": "Fuel",
          "PermissionKey": "Administration:General"
        },
        {
          "Tablename": "dbo.Month",
          "Identifier": "Month",
          "Module": "AdminModule",
          "PermissionKey": "Administration:General"
        },
        {
          "Tablename": "dbo.MonthlyPeriod",
          "Identifier": "MonthlyPeriod",
          "Module": "Occurrence",
          "PermissionKey": "Administration:General"
        }
      ]
    }
  ],
  "UpgradeInfo": {
    "InitialType": "Community",
    "InitialVersion": "5.0.51.8"
  }
}